crystalbleu.py
crystalbleu-0.2.dist-info/licenses/LICENSE
crystalbleu-0.2.dist-info/WHEEL
crystalbleu-0.2.dist-info/METADATA
crystalbleu-0.2.dist-info/RECORD
