Metadata-Version: 2.4
Name: crystalbleu
Version: 0.2
Summary: CrystalBLEU score implementation.
Author-email: Aryaz Eghbali <aryaz.egh@gmail.com>, Michael Pradel <michael@binaervarianz.de>
Classifier: License :: OSI Approved :: Apache Software License
License-File: LICENSE
Project-URL: Home, https://github.com/sola-st/crystalbleu
